MANIFEST.in
README.rst
setup.py
collective/__init__.py
collective.lastmodifier.egg-info/PKG-INFO
collective.lastmodifier.egg-info/SOURCES.txt
collective.lastmodifier.egg-info/dependency_links.txt
collective.lastmodifier.egg-info/entry_points.txt
collective.lastmodifier.egg-info/namespace_packages.txt
collective.lastmodifier.egg-info/not-zip-safe
collective.lastmodifier.egg-info/requires.txt
collective.lastmodifier.egg-info/top_level.txt
collective/lastmodifier/__init__.py
collective/lastmodifier/adapter.py
collective/lastmodifier/configure.zcml
collective/lastmodifier/hooks.py
collective/lastmodifier/indexers.py
collective/lastmodifier/interfaces.py
collective/lastmodifier/patches.py
collective/lastmodifier/schemaextender.py
collective/lastmodifier/subscribers.py
collective/lastmodifier/testing.py
collective/lastmodifier/utils.py
collective/lastmodifier/Extensions/install.py
collective/lastmodifier/profiles/default/catalog.xml
collective/lastmodifier/profiles/default/metadata.xml
collective/lastmodifier/profiles/default/portal_atct.xml
collective/lastmodifier/profiles/uninstall/catalog.xml
collective/lastmodifier/profiles/uninstall/portal_atct.xml
collective/lastmodifier/tests/__init__.py
collective/lastmodifier/tests/builders.py
collective/lastmodifier/tests/profiles.zcml
collective/lastmodifier/tests/test_archetypes_field.py
collective/lastmodifier/tests/test_at_adapter.py
collective/lastmodifier/tests/test_catalog.py
collective/lastmodifier/tests/test_dx_adapter.py
collective/lastmodifier/tests/test_uninstall.py
collective/lastmodifier/tests/profiles/dxtype/metadata.xml
collective/lastmodifier/tests/profiles/dxtype/types.xml
collective/lastmodifier/tests/profiles/dxtype/types/DexterityType.xml
docs/HISTORY.txt
docs/INSTALL.txt
docs/LICENSE.GPL
docs/LICENSE.txt