Metadata-Version: 2.1
Name: collective.lastmodifier
Version: 1.1.3
Summary: Extends Plone content with metadata about the last modifier
Home-page: https://github.com/4teamwork/collective.lastmodifier
Author: 4teamwork AG
Author-email: mailto:info@4teamwork.ch
License: GPL2
Platform: UNKNOWN
Classifier: Framework :: Plone
Classifier: Framework :: Plone :: 4.3
Classifier: Programming Language :: Python
Provides-Extra: tests
